Lab2/LAB2_16BITS/SOURCE/ROM_Process.vhd
library work;
use work.misc.all;


LIBRARY IEEE;
USE IEEE.std_logic_1164.all;
use ieee.std_logic_unsigned.all;
use ieee.std_logic_arith.all;  


ENTITY ROM_Process IS
    generic( filter_taps: integer :=5;
           width      : integer :=16); 
PORT ( 

address : in std_logic_vector(log2_ceil(filter_taps) downto 0);
coeficient_out: out std_logic_vector(width-1 downto 0)
);
end ROM_Process;

architecture ROM_Process_behavioural of ROM_Process is
    type fixed_type is array (0 to filter_taps-1) of std_logic_vector(width-1 downto 0);
--    type fixed_type is array (0 to 8-1) of std_logic_vector(width-1 downto 0);

constant coeff_array : fixed_type :=
(
         ("0000000000000001"),-- 0
         ("0000000000000010"),-- 1
         ("0000000000000011"),-- 2
         ("0000000000000100"),-- 3
         ("0000000000001000")-- 8
 );
begin
    

      coeficient_out <= coeff_array (conv_integer(unsigned(address)));
                    
end ROM_Process_behavioural;

Lab2/LAB2_16BITS/SOURCE/FIR_Processor.vhd
library IEEE;
use IEEE.std_logic_1164.all;
use ieee.std_logic_unsigned.all;
use ieee.std_logic_arith.all;

library work;
use work.misc.all;

entity FIR_Processor is
  generic(filter_taps : integer := 5;
          width       : integer := 16);  
  port (rst_n           : in  std_logic;
        clk             : in  std_logic;
        sample_clk      : in  std_logic;
      --  sample          : in  std_logic_vector(width-1 downto 0);
        sample_delay_in : in  std_logic_vector(width-1 downto 0);
        coeficient      : in  std_logic_vector(width-1 downto 0);
        coef_addr       : out std_logic_vector(log2_ceil(filter_taps) downto 0);
        dav             : out std_logic;

        outp : out std_logic_vector(width-1 downto 0)
        );
end FIR_Processor;

architecture FIR_Processor_behavioural of FIR_Processor is
  
  type state_type is (s0, s1);  --s2,s3,s4,s5); -- List all your states here

  signal CURRENT_STATE, NEXT_STATE : state_type;
  signal accumulator               : std_logic_vector(width*2-1 downto 0):= (others => '0');
  signal dav_wire                  : std_logic:= '0';
  signal outp_wire                 : std_logic_vector(width-1 downto 0):= (others => '0');
  signal coef_addr_wire            : std_logic_vector(log2_ceil(filter_taps) downto 0):= (others => '0');
  signal counter                   : integer:= filter_taps;
  
begin
  
  dav       <= dav_wire;
  outp      <= outp_wire;
  coef_addr <= coef_addr_wire;

  ---------------------------------------------------------
  --Next state logic process      
  combi : process (CURRENT_STATE, sample_clk, counter)
  begin
    case CURRENT_STATE is
      
      when S0 =>
        if sample_clk = '1' then
          NEXT_STATE <= S1;
        else
          NEXT_STATE <= S0;
        end if;
        
      when S1 =>
        
        if (counter = 1) then
          NEXT_STATE <= S0;
        else
          NEXT_STATE <= S1;
        end if;
        
           
    end case;
  end process;  -- combi
-----------------------------------------------------
  --State register process       
  seq : process (clk, rst_n)
  begin
    if rst_n = '0' then
      CURRENT_STATE <= S0;
       counter<=filter_taps;
          
    elsif clk'event and clk = '1' then
      CURRENT_STATE <= NEXT_STATE;
      if (sample_clk = '1') then
        counter <= filter_taps;
      else
        counter <= counter-1;
      end if;
    end if;
  end process seq;
-------------------------------------------------------
--Moore Output process
  output : process (clk, rst_n)
    --variable counter: integer := 'n';
  begin
    
    if rst_n = '0' then
       dav_wire    <= '1';
       outp_wire   <= (others=>'0');
       Accumulator <= (others => '0');
       coef_addr_wire<="000";
    elsif clk'event and clk = '1' then
    
    case current_state is
      
      when s0 =>
        
        dav_wire    <= '1';
        outp_wire   <= Accumulator((width-1) downto 0);
        Accumulator <= (others => '0');
        coef_addr_wire<="000";
        
      when s1 =>
        dav_wire       <= '0';
     

        if (counter = filter_taps) then
          Accumulator <=  (others => '0'); --(sample * coeficient) + Accumulator;
          coef_addr_wire <= "000";
        else
          coef_addr_wire <= coef_addr_wire + 1;
         
          Accumulator    <= (sample_delay_in * coeficient) + Accumulator;
        end if;
        
    end case;
   end if;
  end process output;
  
end architecture;

Lab2/LAB2_16BITS/SOURCE/SRAM.vhd
library ieee;
use ieee.std_logic_1164.all;
use ieee.std_logic_arith.all;

library work;
use work.misc.all;

entity SRAM is
  
 -- generic (n: natural range 8 to 32;
   --        m: natural range 8 to 64);
generic(filter_taps: integer:=5;
         width     : integer:=16);
  port (rst_n : in std_logic;
        rws   : in std_logic;
        addrs : in std_logic_vector (log2_ceil(filter_taps) downto 0);
        inp   : in std_logic_vector (width-1 downto 0);
        outp  : out std_logic_vector (width-1 downto 0));


end SRAM;

architecture SRAM_behaviour of SRAM is
--- synopsys synthesis_off
--- synopsys synthesis_on
  type mem_type is array (0 to filter_taps-1) of std_logic_vector (width-1 downto 0);

 
begin  -- beh

  rw: process (rws, addrs, inp, rst_n)
   variable mem2 : mem_type := (others => (others => '0'));
    
  begin  -- process rd
    if rst_n ='0' then
       mem2 := (others => (others => '0'));
       outp<=(others=>'0');
    elsif rws = '1' then
      outp <= mem2 (conv_integer (unsigned (addrs)));
    else
      mem2 (conv_integer (unsigned (addrs))) := inp;
    end if;
  end process rw;

end SRAM_behaviour;

Lab2/LAB2_16BITS/SOURCE/DelayLine_CB.vhd
library IEEE;
use IEEE.std_logic_1164.all;
use ieee.std_logic_unsigned.all;
use ieee.std_logic_arith.all;

library work;
use work.misc.all;


entity Delayline_CB is
  generic(filter_taps : integer := 5;
          width       : integer := 16);
  port (rst_n      : in  std_logic;
        clk        : in  std_logic;
        sample_clk : in  std_logic;
        sample     : in  std_logic_vector(width-1 downto 0);
        sample_out : out std_logic_vector(width-1 downto 0)
        );
end Delayline_CB;

architecture Delayline_CB_behavioural of Delayline_CB is
  component SRAM
    
    port (rst_n   : in  std_logic;
          rws   : in  std_logic;
          addrs : in  std_logic_vector (log2_ceil(filter_taps) downto 0);
          inp   : in  std_logic_vector (width-1 downto 0);
          outp  : out std_logic_vector(width-1 downto 0));

    
  end component;

  signal rws_wire                         : std_logic;
  signal adrs_wire                        : std_logic_vector(log2_ceil(filter_taps) downto 0) ;-- := (others => '0');
  signal counter , pointer, digit_counter : integer                                           ;-- := filter_taps;

  signal sample_write, sample_out_wire: std_logic_vector(width-1 downto 0);

begin
  
  U30_CBRAM : SRAM port map (rst_n, rws_wire, adrs_wire, sample_write, sample_out_wire);

  sample_out <= sample_out_wire;
  counter_process : process(rst_n, clk)
  begin
    if rst_n = '0' then
      counter <= 0;
      digit_counter <= 0;
      pointer   <= 0;                   -- (others=>'0');
      adrs_wire <= (others => '0');
      sample_write <= (others => '0');
      rws_wire <= '1';
      
    elsif clk'event and clk = '1' then
     --if sample clock 
      if sample_clk = '1' then        
        counter       <= pointer;
        digit_counter <= 0;      
        sample_write <= sample;  
        
        adrs_wire    <= (conv_std_logic_vector(pointer, (log2_ceil(filter_taps)+1)));
        rws_wire <= '0';
         
        if(pointer = 0) then
          pointer <= filter_taps-1;
        else
          pointer <= pointer-1;
        end if;  
         sample_write <= sample;
        
      --else  
      elsif counter = filter_taps-1 then
        counter <= 0;
        digit_counter <= digit_counter+1;
        adrs_wire    <= (conv_std_logic_vector(counter, (log2_ceil(filter_taps)+1)));
         rws_wire <= '1';
      else
        counter       <= counter + 1;
        digit_counter <= digit_counter+1;
        adrs_wire    <= (conv_std_logic_vector(counter, (log2_ceil(filter_taps)+1)));
         rws_wire <= '1';
      end if;
      
    end if;
  end process;

 
  
end Delayline_CB_behavioural;

Lab2/LAB2_16BITS/SOURCE/FIR_Toplevel.vhd
library IEEE;
use IEEE.std_logic_1164.all;
use ieee.std_logic_unsigned.all;
use ieee.std_logic_arith.all;

library work;
use work.misc.all;

entity FIR_Toplevel is
  generic(width       : integer := 16;
          filter_taps : integer := 5);
  port (rst_n      : in std_logic;
        clk        : in std_logic;
        sample_clk : in std_logic;
        sample     : in std_logic_vector(width-1 downto 0);

        dav  : out std_logic;
        outp : out std_logic_vector(width-1 downto 0)
        );
end FIR_Toplevel;

architecture FIR_Toplevel_behavioural of FIR_Toplevel is
  
  component FIR_Processor
    port (rst_n      : in std_logic;
          clk        : in std_logic;
          sample_clk : in std_logic;

         -- sample          : in std_logic_vector(width-1 downto 0);
          sample_delay_in : in std_logic_vector(width-1 downto 0);
          coeficient      : in std_logic_vector(width-1 downto 0);

          coef_addr : out std_logic_vector(log2_ceil(filter_taps) downto 0);
          dav       : out std_logic;
          outp      : out std_logic_vector(width-1 downto 0)
          );
  end component;

  component ROM_Process
    port (address        : in  std_logic_vector(log2_ceil(filter_taps) downto 0);
          coeficient_out : out std_logic_vector(width-1 downto 0)
          );
  end component;

  component Delayline_CB
    port (rst_n      : in  std_logic;
          clk        : in  std_logic;
          sample_clk : in  std_logic;
          sample     : in  std_logic_vector(width-1 downto 0);
          sample_out : out std_logic_vector(width-1 downto 0)
          );
  end component;

  signal coeficient_out_wire : std_logic_vector(width-1 downto 0);
  signal sample_out_wire     : std_logic_vector(width-1 downto 0);
  signal outp_wire           : std_logic_vector(width-1 downto 0);
  signal coef_addr_wire      : std_logic_vector(log2_ceil(filter_taps) downto 0);
  signal dav_wire            : std_logic;

begin

  dav  <= dav_wire;
  outp <= outp_wire;

  U_delayline : DelayLine_CB port map (rst_n, clk, sample_clk, sample, sample_out_wire);
  u_FIRP      : FIR_processor port map (rst_n, clk, sample_clk, sample_out_wire, coeficient_out_wire, coef_addr_wire, dav_wire, outp_wire);
  u_ROM       : ROM_process port map (coef_addr_wire, coeficient_out_wire);
  
  
end architecture FIR_Toplevel_behavioural;

Lab2/LAB2_16BITS/SOURCE/tb_FIR.vhd
library IEEE;
use IEEE.std_logic_1164.all;
use IEEE.std_logic_unsigned.all;
use IEEE.std_logic_arith.all;
use IEEE.math_real.all;

entity tb_FIR is
end entity tb_FIR;

architecture tb_FIR_behavioural of tb_FIR is
  constant clk_period : time     := 2.5 ns;
  constant nr_of_taps : positive := 5;
  constant width      : positive := 16;

  component FIR_Toplevel
    port (rst_n      : in std_logic;
          clk        : in std_logic;
          sample_clk : in std_logic;
          sample     : in std_logic_vector(15 downto 0);
          dav  : out std_logic;
          outp : out std_logic_vector(15 downto 0)
          );
  end component;

  signal clk, sample_clk        : std_logic := '0';
  signal rst_n, dav_wire        : std_logic;
  signal sample_wire, outp_wire : std_logic_vector(15 downto 0);

begin

  rst_n <= '0', '1' after 2 ns;
  
  clk <= not clk after clk_period/2;

  random_generator:process 
			VARIABLE seed1	    :	positive        := 1; 
			VARIABLE seed2	    :	positive        := 15; 
			VARIABLE a_real   	: real; 
			VARIABLE count     : INTEGER         := 0; 
			VARIABLE number_of_samples : INTEGER := 5000;
			begin 
					for j in 1 to number_of_samples loop 
							wait until sample_clk'event and sample_clk = '1'; 
							unIFORm(seed1,seed2,a_real); 
							a_real := a_real * 16.0; 
							if(count < number_of_samples) then 
									sample_wire <= conv_std_logic_vector(INTEGER(a_real), 16) ; 
									count := count+1;
							end if;
					end loop; 
 end process random_generator;




  smpl_clk : process

  begin  -- process smpl_clk

    sample_clk <= '0';

    for i in 1 to nr_of_taps loop
      wait until clk'event and clk = '0';
    end loop;  -- iwait until clk'event and clk = '1';

    sample_clk <= '1';

    wait until clk'event and clk = '0';
    
  end process smpl_clk;

  --sample_wire <= (others => '0'),
  --               conv_std_logic_vector (1, width-1) after (nr_of_taps*clk_period),
  --               conv_std_logic_vector (0, width-1) after ((nr_of_taps+1)*clk_period),
  --               conv_std_logic_vector (2, width-1) after ((2*nr_of_taps+1)*clk_period),
  --               (others => '0') after ((2*nr_of_taps+2)*clk_period);

  
  u1 : FIR_Toplevel port map(rst_n, clk, sample_clk, sample_wire, dav_wire, outp_wire);

end tb_FIR_behavioural;

Lab2/LAB2_16BITS/REPORTS/top_fir_samples5.vcd
$date
	Tue Nov 24 20:23:55 2015
$end
$version
	ModelSim Version 6.5
$end
$timescale
	1ns
$end
$scope module tb_fir $end
$var wire 1 ! clk $end
$var wire 1 " sample_clk $end
$var wire 1 # rst_n $end
$var wire 1 $ dav_wire $end
$var wire 1 % sample_wire [15] $end
$var wire 1 & sample_wire [14] $end
$var wire 1 ' sample_wire [13] $end
$var wire 1 ( sample_wire [12] $end
$var wire 1 ) sample_wire [11] $end
$var wire 1 * sample_wire [10] $end
$var wire 1 + sample_wire [9] $end
$var wire 1 , sample_wire [8] $end
$var wire 1 - sample_wire [7] $end
$var wire 1 . sample_wire [6] $end
$var wire 1 / sample_wire [5] $end
$var wire 1 0 sample_wire [4] $end
$var wire 1 1 sample_wire [3] $end
$var wire 1 2 sample_wire [2] $end
$var wire 1 3 sample_wire [1] $end
$var wire 1 4 sample_wire [0] $end
$var wire 1 5 outp_wire [15] $end
$var wire 1 6 outp_wire [14] $end
$var wire 1 7 outp_wire [13] $end
$var wire 1 8 outp_wire [12] $end
$var wire 1 9 outp_wire [11] $end
$var wire 1 : outp_wire [10] $end
$var wire 1 ; outp_wire [9] $end
$var wire 1 < outp_wire [8] $end
$var wire 1 = outp_wire [7] $end
$var wire 1 > outp_wire [6] $end
$var wire 1 ? outp_wire [5] $end
$var wire 1 @ outp_wire [4] $end
$var wire 1 A outp_wire [3] $end
$var wire 1 B outp_wire [2] $end
$var wire 1 C outp_wire [1] $end
$var wire 1 D outp_wire [0] $end
$scope module u1 $end
$var wire 1 # rst_n $end
$var wire 1 ! clk $end
$var wire 1 " sample_clk $end
$var wire 1 % sample [15] $end
$var wire 1 & sample [14] $end
$var wire 1 ' sample [13] $end
$var wire 1 ( sample [12] $end
$var wire 1 ) sample [11] $end
$var wire 1 * sample [10] $end
$var wire 1 + sample [9] $end
$var wire 1 , sample [8] $end
$var wire 1 - sample [7] $end
$var wire 1 . sample [6] $end
$var wire 1 / sample [5] $end
$var wire 1 0 sample [4] $end
$var wire 1 1 sample [3] $end
$var wire 1 2 sample [2] $end
$var wire 1 3 sample [1] $end
$var wire 1 4 sample [0] $end
$var wire 1 $ dav $end
$var wire 1 5 outp [15] $end
$var wire 1 6 outp [14] $end
$var wire 1 7 outp [13] $end
$var wire 1 8 outp [12] $end
$var wire 1 9 outp [11] $end
$var wire 1 : outp [10] $end
$var wire 1 ; outp [9] $end
$var wire 1 < outp [8] $end
$var wire 1 = outp [7] $end
$var wire 1 > outp [6] $end
$var wire 1 ? outp [5] $end
$var wire 1 @ outp [4] $end
$var wire 1 A outp [3] $end
$var wire 1 B outp [2] $end
$var wire 1 C outp [1] $end
$var wire 1 D outp [0] $end
$var wire 1 E coeficient_out_wire [15] $end
$var wire 1 F coeficient_out_wire [14] $end
$var wire 1 G coeficient_out_wire [13] $end
$var wire 1 H coeficient_out_wire [12] $end
$var wire 1 I coeficient_out_wire [11] $end
$var wire 1 J coeficient_out_wire [10] $end
$var wire 1 K coeficient_out_wire [9] $end
$var wire 1 L coeficient_out_wire [8] $end
$var wire 1 M coeficient_out_wire [7] $end
$var wire 1 N coeficient_out_wire [6] $end
$var wire 1 O coeficient_out_wire [5] $end
$var wire 1 P coeficient_out_wire [4] $end
$var wire 1 Q coeficient_out_wire [3] $end
$var wire 1 R coeficient_out_wire [2] $end
$var wire 1 S coeficient_out_wire [1] $end
$var wire 1 T coeficient_out_wire [0] $end
$var wire 1 U sample_out_wire [15] $end
$var wire 1 V sample_out_wire [14] $end
$var wire 1 W sample_out_wire [13] $end
$var wire 1 X sample_out_wire [12] $end
$var wire 1 Y sample_out_wire [11] $end
$var wire 1 Z sample_out_wire [10] $end
$var wire 1 [ sample_out_wire [9] $end
$var wire 1 \ sample_out_wire [8] $end
$var wire 1 ] sample_out_wire [7] $end
$var wire 1 ^ sample_out_wire [6] $end
$var wire 1 _ sample_out_wire [5] $end
$var wire 1 ` sample_out_wire [4] $end
$var wire 1 a sample_out_wire [3] $end
$var wire 1 b sample_out_wire [2] $end
$var wire 1 c sample_out_wire [1] $end
$var wire 1 d sample_out_wire [0] $end
$var wire 1 e outp_wire [15] $end
$var wire 1 f outp_wire [14] $end
$var wire 1 g outp_wire [13] $end
$var wire 1 h outp_wire [12] $end
$var wire 1 i outp_wire [11] $end
$var wire 1 j outp_wire [10] $end
$var wire 1 k outp_wire [9] $end
$var wire 1 l outp_wire [8] $end
$var wire 1 m outp_wire [7] $end
$var wire 1 n outp_wire [6] $end
$var wire 1 o outp_wire [5] $end
$var wire 1 p outp_wire [4] $end
$var wire 1 q outp_wire [3] $end
$var wire 1 r outp_wire [2] $end
$var wire 1 s outp_wire [1] $end
$var wire 1 t outp_wire [0] $end
$var wire 1 u coef_addr_wire [2] $end
$var wire 1 v coef_addr_wire [1] $end
$var wire 1 w coef_addr_wire [0] $end
$var wire 1 x dav_wire $end
$scope module u_delayline $end
$var wire 1 # rst_n $end
$var wire 1 ! clk $end
$var wire 1 " sample_clk $end
$var wire 1 % sample [15] $end
$var wire 1 & sample [14] $end
$var wire 1 ' sample [13] $end
$var wire 1 ( sample [12] $end
$var wire 1 ) sample [11] $end
$var wire 1 * sample [10] $end
$var wire 1 + sample [9] $end
$var wire 1 , sample [8] $end
$var wire 1 - sample [7] $end
$var wire 1 . sample [6] $end
$var wire 1 / sample [5] $end
$var wire 1 0 sample [4] $end
$var wire 1 1 sample [3] $end
$var wire 1 2 sample [2] $end
$var wire 1 3 sample [1] $end
$var wire 1 4 sample [0] $end
$var wire 1 U sample_out [15] $end
$var wire 1 V sample_out [14] $end
$var wire 1 W sample_out [13] $end
$var wire 1 X sample_out [12] $end
$var wire 1 Y sample_out [11] $end
$var wire 1 Z sample_out [10] $end
$var wire 1 [ sample_out [9] $end
$var wire 1 \ sample_out [8] $end
$var wire 1 ] sample_out [7] $end
$var wire 1 ^ sample_out [6] $end
$var wire 1 _ sample_out [5] $end
$var wire 1 ` sample_out [4] $end
$var wire 1 a sample_out [3] $end
$var wire 1 b sample_out [2] $end
$var wire 1 c sample_out [1] $end
$var wire 1 d sample_out [0] $end
$var wire 1 y rws_wire $end
$var wire 1 z adrs_wire [2] $end
$var wire 1 { adrs_wire [1] $end
$var wire 1 | adrs_wire [0] $end
$var wire 1 } sample_write [15] $end
$var wire 1 ~ sample_write [14] $end
$var wire 1 !! sample_write [13] $end
$var wire 1 "! sample_write [12] $end
$var wire 1 #! sample_write [11] $end
$var wire 1 $! sample_write [10] $end
$var wire 1 %! sample_write [9] $end
$var wire 1 &! sample_write [8] $end
$var wire 1 '! sample_write [7] $end
$var wire 1 (! sample_write [6] $end
$var wire 1 )! sample_write [5] $end
$var wire 1 *! sample_write [4] $end
$var wire 1 +! sample_write [3] $end
$var wire 1 ,! sample_write [2] $end
$var wire 1 -! sample_write [1] $end
$var wire 1 .! sample_write [0] $end
$var wire 1 /! sample_out_wire [15] $end
$var wire 1 0! sample_out_wire [14] $end
$var wire 1 1! sample_out_wire [13] $end
$var wire 1 2! sample_out_wire [12] $end
$var wire 1 3! sample_out_wire [11] $end
$var wire 1 4! sample_out_wire [10] $end
$var wire 1 5! sample_out_wire [9] $end
$var wire 1 6! sample_out_wire [8] $end
$var wire 1 7! sample_out_wire [7] $end
$var wire 1 8! sample_out_wire [6] $end
$var wire 1 9! sample_out_wire [5] $end
$var wire 1 :! sample_out_wire [4] $end
$var wire 1 ;! sample_out_wire [3] $end
$var wire 1 <! sample_out_wire [2] $end
$var wire 1 =! sample_out_wire [1] $end
$var wire 1 >! sample_out_wire [0] $end
$scope module u30_cbram $end
$var wire 1 # rst_n $end
$var wire 1 y rws $end
$var wire 1 z addrs [2] $end
$var wire 1 { addrs [1] $end
$var wire 1 | addrs [0] $end
$var wire 1 } inp [15] $end
$var wire 1 ~ inp [14] $end
$var wire 1 !! inp [13] $end
$var wire 1 "! inp [12] $end
$var wire 1 #! inp [11] $end
$var wire 1 $! inp [10] $end
$var wire 1 %! inp [9] $end
$var wire 1 &! inp [8] $end
$var wire 1 '! inp [7] $end
$var wire 1 (! inp [6] $end
$var wire 1 )! inp [5] $end
$var wire 1 *! inp [4] $end
$var wire 1 +! inp [3] $end
$var wire 1 ,! inp [2] $end
$var wire 1 -! inp [1] $end
$var wire 1 .! inp [0] $end
$var wire 1 /! outp [15] $end
$var wire 1 0! outp [14] $end
$var wire 1 1! outp [13] $end
$var wire 1 2! outp [12] $end
$var wire 1 3! outp [11] $end
$var wire 1 4! outp [10] $end
$var wire 1 5! outp [9] $end
$var wire 1 6! outp [8] $end
$var wire 1 7! outp [7] $end
$var wire 1 8! outp [6] $end
$var wire 1 9! outp [5] $end
$var wire 1 :! outp [4] $end
$var wire 1 ;! outp [3] $end
$var wire 1 <! outp [2] $end
$var wire 1 =! outp [1] $end
$var wire 1 >! outp [0] $end
$upscope $end
$upscope $end
$scope module u_firp $end
$var wire 1 # rst_n $end
$var wire 1 ! clk $end
$var wire 1 " sample_clk $end
$var wire 1 U sample_delay_in [15] $end
$var wire 1 V sample_delay_in [14] $end
$var wire 1 W sample_delay_in [13] $end
$var wire 1 X sample_delay_in [12] $end
$var wire 1 Y sample_delay_in [11] $end
$var wire 1 Z sample_delay_in [10] $end
$var wire 1 [ sample_delay_in [9] $end
$var wire 1 \ sample_delay_in [8] $end
$var wire 1 ] sample_delay_in [7] $end
$var wire 1 ^ sample_delay_in [6] $end
$var wire 1 _ sample_delay_in [5] $end
$var wire 1 ` sample_delay_in [4] $end
$var wire 1 a sample_delay_in [3] $end
$var wire 1 b sample_delay_in [2] $end
$var wire 1 c sample_delay_in [1] $end
$var wire 1 d sample_delay_in [0] $end
$var wire 1 E coeficient [15] $end
$var wire 1 F coeficient [14] $end
$var wire 1 G coeficient [13] $end
$var wire 1 H coeficient [12] $end
$var wire 1 I coeficient [11] $end
$var wire 1 J coeficient [10] $end
$var wire 1 K coeficient [9] $end
$var wire 1 L coeficient [8] $end
$var wire 1 M coeficient [7] $end
$var wire 1 N coeficient [6] $end
$var wire 1 O coeficient [5] $end
$var wire 1 P coeficient [4] $end
$var wire 1 Q coeficient [3] $end
$var wire 1 R coeficient [2] $end
$var wire 1 S coeficient [1] $end
$var wire 1 T coeficient [0] $end
$var wire 1 u coef_addr [2] $end
$var wire 1 v coef_addr [1] $end
$var wire 1 w coef_addr [0] $end
$var wire 1 x dav $end
$var wire 1 e outp [15] $end
$var wire 1 f outp [14] $end
$var wire 1 g outp [13] $end
$var wire 1 h outp [12] $end
$var wire 1 i outp [11] $end
$var wire 1 j outp [10] $end
$var wire 1 k outp [9] $end
$var wire 1 l outp [8] $end
$var wire 1 m outp [7] $end
$var wire 1 n outp [6] $end
$var wire 1 o outp [5] $end
$var wire 1 p outp [4] $end
$var wire 1 q outp [3] $end
$var wire 1 r outp [2] $end
$var wire 1 s outp [1] $end
$var wire 1 t outp [0] $end
$var wire 1 ?! accumulator [31] $end
$var wire 1 @! accumulator [30] $end
$var wire 1 A! accumulator [29] $end
$var wire 1 B! accumulator [28] $end
$var wire 1 C! accumulator [27] $end
$var wire 1 D! accumulator [26] $end
$var wire 1 E! accumulator [25] $end
$var wire 1 F! accumulator [24] $end
$var wire 1 G! accumulator [23] $end
$var wire 1 H! accumulator [22] $end
$var wire 1 I! accumulator [21] $end
$var wire 1 J! accumulator [20] $end
$var wire 1 K! accumulator [19] $end
$var wire 1 L! accumulator [18] $end
$var wire 1 M! accumulator [17] $end
$var wire 1 N! accumulator [16] $end
$var wire 1 O! accumulator [15] $end
$var wire 1 P! accumulator [14] $end
$var wire 1 Q! accumulator [13] $end
$var wire 1 R! accumulator [12] $end
$var wire 1 S! accumulator [11] $end
$var wire 1 T! accumulator [10] $end
$var wire 1 U! accumulator [9] $end
$var wire 1 V! accumulator [8] $end
$var wire 1 W! accumulator [7] $end
$var wire 1 X! accumulator [6] $end
$var wire 1 Y! accumulator [5] $end
$var wire 1 Z! accumulator [4] $end
$var wire 1 [! accumulator [3] $end
$var wire 1 \! accumulator [2] $end
$var wire 1 ]! accumulator [1] $end
$var wire 1 ^! accumulator [0] $end
$var wire 1 _! dav_wire $end
$var wire 1 `! outp_wire [15] $end
$var wire 1 a! outp_wire [14] $end
$var wire 1 b! outp_wire [13] $end
$var wire 1 c! outp_wire [12] $end
$var wire 1 d! outp_wire [11] $end
$var wire 1 e! outp_wire [10] $end
$var wire 1 f! outp_wire [9] $end
$var wire 1 g! outp_wire [8] $end
$var wire 1 h! outp_wire [7] $end
$var wire 1 i! outp_wire [6] $end
$var wire 1 j! outp_wire [5] $end
$var wire 1 k! outp_wire [4] $end
$var wire 1 l! outp_wire [3] $end
$var wire 1 m! outp_wire [2] $end
$var wire 1 n! outp_wire [1] $end
$var wire 1 o! outp_wire [0] $end
$var wire 1 p! coef_addr_wire [2] $end
$var wire 1 q! coef_addr_wire [1] $end
$var wire 1 r! coef_addr_wire [0] $end
$upscope $end
$scope module u_rom $end
$var wire 1 u address [2] $end
$var wire 1 v address [1] $end
$var wire 1 w address [0] $end
$var wire 1 E coeficient_out [15] $end
$var wire 1 F coeficient_out [14] $end
$var wire 1 G coeficient_out [13] $end
$var wire 1 H coeficient_out [12] $end
$var wire 1 I coeficient_out [11] $end
$var wire 1 J coeficient_out [10] $end
$var wire 1 K coeficient_out [9] $end
$var wire 1 L coeficient_out [8] $end
$var wire 1 M coeficient_out [7] $end
$var wire 1 N coeficient_out [6] $end
$var wire 1 O coeficient_out [5] $end
$var wire 1 P coeficient_out [4] $end
$var wire 1 Q coeficient_out [3] $end
$var wire 1 R coeficient_out [2] $end
$var wire 1 S coeficient_out [1] $end
$var wire 1 T coeficient_out [0] $end
$upscope $end
$upscope $end
$upscope $end
$enddefinitions $end
#20
$dumpvars
0!
0"
1#
0$
0x
1y
0_!
0%
0&
0'
0(
0)
0*
0+
0,
0-
0.
0/
10
01
02
03
04
05
06
07
08
09
0:
0;
0<
0=
0>
0?
0@
0A
0B
0C
0D
0E
0F
0G
0H
0I
0J
0K
0L
0M
0N
0O
0P
0Q
1R
0S
0T
0U
0V
0W
0X
0Y
0Z
0[
0\
0]
0^
0_
0`
0a
0b
0c
0d
0e
0f
0g
0h
0i
0j
0k
0l
0m
0n
0o
0p
0q
0r
0s
0t
0u
1v
1w
0z
1{
1|
0}
0~
0!!
0"!
0#!
0$!
0%!
0&!
0'!
0(!
0)!
1*!
0+!
0,!
0-!
0.!
0/!
00!
01!
02!
03!
04!
05!
06!
07!
08!
09!
0:!
0;!
0<!
0=!
0>!
0?!
0@!
0A!
0B!
0C!
0D!
0E!
0F!
0G!
0H!
0I!
0J!
0K!
0L!
0M!
0N!
0O!
0P!
0Q!
0R!
0S!
0T!
0U!
0V!
0W!
0X!
0Y!
1Z!
0[!
0\!
0]!
0^!
0`!
0a!
0b!
0c!
0d!
0e!
0f!
0g!
0h!
0i!
0j!
0k!
0l!
0m!
0n!
0o!
0p!
1q!
1r!
$end
#21
1!
0|
0{
1z
0r!
0q!
1p!
0w
0v
1u
0R
1Q
#22
0!
1"
14
13
00
#23
1!
0y
1.!
1-!
0*!
0p!
0Z!
1k!
1_!
0u
1p
1x
1T
0Q
1@
1$
#24
0!
0"
#25
1!
1y
0_!
1>!
1=!
0x
1d
1c
0$
#26
0!
#27
1!
0z
1^!
1]!
1r!
0>!
0=!
1:!
1w
0d
0c
1`
0T
1S
#28
0!
#29
1!
1|
1Y!
0r!
1q!
0:!
0w
1v
0`
1T
#30
0!
#31
1!
0|
1{
1r!
1w
0T
0S
1R
#32
0!
#33
1!
1|
0r!
0q!
1p!
0w
0v
1u
0R
1Q
#34
0!
1"
12
11
#35
1!
0y
1,!
1+!
0p!
0^!
0]!
0Y!
1o!
1n!
0k!
1j!
1_!
0u
1t
1s
0p
1o
1x
1T
0Q
1D
1C
0@
1?
1$
#36
0!
0"
#37
1!
1y
0_!
1>!
1=!
1<!
1;!
0x
1d
1c
1b
1a
0$
#38
0!
#39
1!
0|
0{
1z
1^!
1]!
1\!
1[!
1r!
0<!
0;!
1w
0b
0a
0T
1S
#40
0!
#41
1!
0z
0]!
0[!
1Z!
0r!
1q!
0>!
0=!
1:!
0w
1v
0d
0c
1`
1T
#42
0!
#43
1!
1|
0Z!
1X!
1r!
0:!
1w
0`
0T
0S
1R
#44
0!
#45
1!
0|
1{
0r!
0q!
1p!
0w
0v
1u
0R
1Q
#46
0!
1"
04
02
01
#47
1!
0y
0.!
0,!
0+!
0p!
0^!
0\!
0X!
0n!
1m!
0j!
1i!
1_!
0u
0s
1r
0o
1n
1x
1T
0Q
0C
1B
0?
1>
1$
#48
0!
0"
#49
1!
1y
0_!
1=!
0x
1c
0$
#50
0!
#51
1!
1|
1]!
1r!
1>!
1<!
1;!
1w
1d
1b
1a
0T
1S
#52
0!
#53
1!
0|
0{
1z
0]!
1Y!
0r!
1q!
0<!
0;!
0w
1v
0b
0a
1T
#54
0!
#55
1!
0z
1^!
1[!
1r!
0>!
0=!
1:!
1w
0d
0c
1`
0T
0S
1R
#56
0!
#57
1!
1|
1X!
0r!
0q!
1p!
0:!
0w
0v
1u
0`
0R
1Q
#58
0!
1"
03
12
11
#59
1!
0y
0-!
1,!
1+!
0p!
0^!
0[!
0Y!
0X!
0m!
1l!
1j!
1_!
0u
0r
1q
1o
1x
1T
0Q
0B
1A
1?
1$
#60
0!
0"
#61
1!
1y
0_!
1<!
1;!
0x
1b
1a
0$
#62
0!
#63
1!
0|
1{
1\!
1[!
1r!
1=!
0<!
0;!
1w
1c
0b
0a
0T
1S
#64
0!
#65
1!
1|
0\!
0[!
1Z!
0r!
1q!
1>!
1<!
1;!
0w
1v
1d
1b
1a
1T
#66
0!
#67
1!
0|
0{
1z
1^!
1\!
1[!
1Y!
1r!
0<!
0;!
1w
0b
0a
0T
0S
1R
#68
0!
#69
1!
0z
0\!
0Z!
0Y!
1X!
0r!
0q!
1p!
0>!
0=!
1:!
0w
0v
1u
0d
0c
1`
0R
1Q
#70
0!
1"
#71
1!
0y
0p!
0^!
0[!
0X!
0j!
1_!
0u
0o
1x
1T
0Q
0?
1$
#72
0!
0"
#73
1!
1y
0_!
1<!
1;!
0:!
0x
1b
1a
0`
0$
#74
0!
#75
1!
1|
1\!
1[!
1r!
1w
0T
1S
#76
0!
