Lab2/LAB2_16BITS/SOURCE/ROM_Process.vhd
library work;
use work.misc.all;


LIBRARY IEEE;
USE IEEE.std_logic_1164.all;
use ieee.std_logic_unsigned.all;
use ieee.std_logic_arith.all;  


ENTITY ROM_Process IS
    generic( filter_taps: integer :=5;
           width      : integer :=16); 
PORT ( 

address : in std_logic_vector(log2_ceil(filter_taps) downto 0);
coeficient_out: out std_logic_vector(width-1 downto 0)
);
end ROM_Process;

architecture ROM_Process_behavioural of ROM_Process is
    type fixed_type is array (0 to filter_taps-1) of std_logic_vector(width-1 downto 0);
--    type fixed_type is array (0 to 8-1) of std_logic_vector(width-1 downto 0);

constant coeff_array : fixed_type :=
(
         ("0000000000000001"),-- 0
         ("0000000000000010"),-- 1
         ("0000000000000011"),-- 2
         ("0000000000000100"),-- 3
         ("0000000000001000")-- 8
 );
begin
    

      coeficient_out <= coeff_array (conv_integer(unsigned(address)));
                    
end ROM_Process_behavioural;

Lab2/LAB2_16BITS/SOURCE/FIR_Processor.vhd
library IEEE;
use IEEE.std_logic_1164.all;
use ieee.std_logic_unsigned.all;
use ieee.std_logic_arith.all;

library work;
use work.misc.all;

entity FIR_Processor is
  generic(filter_taps : integer := 5;
          width       : integer := 16);  
  port (rst_n           : in  std_logic;
        clk             : in  std_logic;
        sample_clk      : in  std_logic;
      --  sample          : in  std_logic_vector(width-1 downto 0);
        sample_delay_in : in  std_logic_vector(width-1 downto 0);
        coeficient      : in  std_logic_vector(width-1 downto 0);
        coef_addr       : out std_logic_vector(log2_ceil(filter_taps) downto 0);
        dav             : out std_logic;

        outp : out std_logic_vector(width-1 downto 0)
        );
end FIR_Processor;

architecture FIR_Processor_behavioural of FIR_Processor is
  
  type state_type is (s0, s1);  --s2,s3,s4,s5); -- List all your states here

  signal CURRENT_STATE, NEXT_STATE : state_type;
  signal accumulator               : std_logic_vector(width*2-1 downto 0):= (others => '0');
  signal dav_wire                  : std_logic:= '0';
  signal outp_wire                 : std_logic_vector(width-1 downto 0):= (others => '0');
  signal coef_addr_wire            : std_logic_vector(log2_ceil(filter_taps) downto 0):= (others => '0');
  signal counter                   : integer:= filter_taps;
  
begin
  
  dav       <= dav_wire;
  outp      <= outp_wire;
  coef_addr <= coef_addr_wire;

  ---------------------------------------------------------
  --Next state logic process      
  combi : process (CURRENT_STATE, sample_clk, counter)
  begin
    case CURRENT_STATE is
      
      when S0 =>
        if sample_clk = '1' then
          NEXT_STATE <= S1;
        else
          NEXT_STATE <= S0;
        end if;
        
      when S1 =>
        
        if (counter = 1) then
          NEXT_STATE <= S0;
        else
          NEXT_STATE <= S1;
        end if;
        
           
    end case;
  end process;  -- combi
-----------------------------------------------------
  --State register process       
  seq : process (clk, rst_n)
  begin
    if rst_n = '0' then
      CURRENT_STATE <= S0;
       counter<=filter_taps;
          
    elsif clk'event and clk = '1' then
      CURRENT_STATE <= NEXT_STATE;
      if (sample_clk = '1') then
        counter <= filter_taps;
      else
        counter <= counter-1;
      end if;
    end if;
  end process seq;
-------------------------------------------------------
--Moore Output process
  output : process (clk, rst_n)
    --variable counter: integer := 'n';
  begin
    
    if rst_n = '0' then
       dav_wire    <= '1';
       outp_wire   <= (others=>'0');
       Accumulator <= (others => '0');
       coef_addr_wire<="000";
    elsif clk'event and clk = '1' then
    
    case current_state is
      
      when s0 =>
        
        dav_wire    <= '1';
        outp_wire   <= Accumulator((width-1) downto 0);
        Accumulator <= (others => '0');
        coef_addr_wire<="000";
        
      when s1 =>
        dav_wire       <= '0';
     

        if (counter = filter_taps) then
          Accumulator <=  (others => '0'); --(sample * coeficient) + Accumulator;
          coef_addr_wire <= "000";
        else
          coef_addr_wire <= coef_addr_wire + 1;
         
          Accumulator    <= (sample_delay_in * coeficient) + Accumulator;
        end if;
        
    end case;
   end if;
  end process output;
  
end architecture;

Lab2/LAB2_16BITS/SOURCE/SRAM.vhd
library ieee;
use ieee.std_logic_1164.all;
use ieee.std_logic_arith.all;

library work;
use work.misc.all;

entity SRAM is
  
 -- generic (n: natural range 8 to 32;
   --        m: natural range 8 to 64);
generic(filter_taps: integer:=5;
         width     : integer:=16);
  port (rst_n : in std_logic;
        rws   : in std_logic;
        addrs : in std_logic_vector (log2_ceil(filter_taps) downto 0);
        inp   : in std_logic_vector (width-1 downto 0);
        outp  : out std_logic_vector (width-1 downto 0));


end SRAM;

architecture SRAM_behaviour of SRAM is
--- synopsys synthesis_off
--- synopsys synthesis_on
  type mem_type is array (0 to filter_taps-1) of std_logic_vector (width-1 downto 0);

 
begin  -- beh

  rw: process (rws, addrs, inp, rst_n)
   variable mem2 : mem_type := (others => (others => '0'));
    
  begin  -- process rd
    if rst_n ='0' then
       mem2 := (others => (others => '0'));
       outp<=(others=>'0');
    elsif rws = '1' then
      outp <= mem2 (conv_integer (unsigned (addrs)));
    else
      mem2 (conv_integer (unsigned (addrs))) := inp;
    end if;
  end process rw;

end SRAM_behaviour;

Lab2/LAB2/SOURCE/DelayLine_CB.vhd
library IEEE;
use IEEE.std_logic_1164.all;
use ieee.std_logic_unsigned.all;
use ieee.std_logic_arith.all;

library work;
use work.misc.all;


entity Delayline_CB is
  generic(filter_taps : integer := 5;
          width       : integer := 4);
  port (rst_n      : in  std_logic;
        clk        : in  std_logic;
        sample_clk : in  std_logic;
        sample     : in  std_logic_vector(width-1 downto 0);
        sample_out : out std_logic_vector(width-1 downto 0)
        );
end Delayline_CB;

architecture Delayline_CB_behavioural of Delayline_CB is
  component SRAM
    
    port (rst_n   : in  std_logic;
          rws   : in  std_logic;
          addrs : in  std_logic_vector (log2_ceil(filter_taps) downto 0);
          inp   : in  std_logic_vector (width-1 downto 0);
          outp  : out std_logic_vector(width-1 downto 0));

    
  end component;

  signal rws_wire                         : std_logic;
  signal adrs_wire                        : std_logic_vector(log2_ceil(filter_taps) downto 0) ;-- := (others => '0');
  signal counter , pointer, digit_counter : integer                                           ;-- := filter_taps;

  signal sample_write, sample_out_wire: std_logic_vector(width-1 downto 0);

begin
  
  U30_CBRAM : SRAM port map (rst_n, rws_wire, adrs_wire, sample_write, sample_out_wire);

  sample_out <= sample_out_wire;
  counter_process : process(rst_n, clk)
  begin
    if rst_n = '0' then
      counter <= 0;
      digit_counter <= 0;
      pointer   <= 0;                   -- (others=>'0');
      adrs_wire <= (others => '0');
      sample_write <= (others => '0');
      rws_wire <= '1';
      
    elsif clk'event and clk = '1' then
     --if sample clock 
      if sample_clk = '1' then        
        counter       <= pointer;
        digit_counter <= 0;      
        sample_write <= sample;  
        
        adrs_wire    <= (conv_std_logic_vector(pointer, (log2_ceil(filter_taps)+1)));
        rws_wire <= '0';
         
        if(pointer = 0) then
          pointer <= filter_taps-1;
        else
          pointer <= pointer-1;
        end if;  
         sample_write <= sample;
        
      --else  
      elsif counter = filter_taps-1 then
        counter <= 0;
        digit_counter <= digit_counter+1;
        adrs_wire    <= (conv_std_logic_vector(counter, (log2_ceil(filter_taps)+1)));
         rws_wire <= '1';
      else
        counter       <= counter + 1;
        digit_counter <= digit_counter+1;
        adrs_wire    <= (conv_std_logic_vector(counter, (log2_ceil(filter_taps)+1)));
         rws_wire <= '1';
      end if;
      
    end if;
  end process;

 
  
end Delayline_CB_behavioural;

Lab2/LAB2/SOURCE/FIR_Toplevel.vhd
library IEEE;
use IEEE.std_logic_1164.all;
use ieee.std_logic_unsigned.all;
use ieee.std_logic_arith.all;

library work;
use work.misc.all;

entity FIR_Toplevel is
  generic(width       : integer := 4;
          filter_taps : integer := 5);
  port (rst_n      : in std_logic;
        clk        : in std_logic;
        sample_clk : in std_logic;
        sample     : in std_logic_vector(width-1 downto 0);

        dav  : out std_logic;
        outp : out std_logic_vector(width-1 downto 0)
        );
end FIR_Toplevel;

architecture FIR_Toplevel_behavioural of FIR_Toplevel is
  
  component FIR_Processor
    port (rst_n      : in std_logic;
          clk        : in std_logic;
          sample_clk : in std_logic;

         -- sample          : in std_logic_vector(width-1 downto 0);
          sample_delay_in : in std_logic_vector(width-1 downto 0);
          coeficient      : in std_logic_vector(width-1 downto 0);

          coef_addr : out std_logic_vector(log2_ceil(filter_taps) downto 0);
          dav       : out std_logic;
          outp      : out std_logic_vector(width-1 downto 0)
          );
  end component;

  component ROM_Process
    port (address        : in  std_logic_vector(log2_ceil(filter_taps) downto 0);
          coeficient_out : out std_logic_vector(width-1 downto 0)
          );
  end component;

  component Delayline_CB
    port (rst_n      : in  std_logic;
          clk        : in  std_logic;
          sample_clk : in  std_logic;
          sample     : in  std_logic_vector(width-1 downto 0);
          sample_out : out std_logic_vector(width-1 downto 0)
          );
  end component;

  signal coeficient_out_wire : std_logic_vector(width-1 downto 0);
  signal sample_out_wire     : std_logic_vector(width-1 downto 0);
  signal outp_wire           : std_logic_vector(width-1 downto 0);
  signal coef_addr_wire      : std_logic_vector(log2_ceil(filter_taps) downto 0);
  signal dav_wire            : std_logic;

begin

  dav  <= dav_wire;
  outp <= outp_wire;

  U_delayline : DelayLine_CB port map (rst_n, clk, sample_clk, sample, sample_out_wire);
  u_FIRP      : FIR_processor port map (rst_n, clk, sample_clk, sample_out_wire, coeficient_out_wire, coef_addr_wire, dav_wire, outp_wire);
  u_ROM       : ROM_process port map (coef_addr_wire, coeficient_out_wire);
  
  
end architecture FIR_Toplevel_behavioural;

Lab2/LAB2/SOURCE/tb_FIR_old.vhd
library IEEE;
use IEEE.std_logic_1164.all;
use IEEE.std_logic_unsigned.all;
use IEEE.std_logic_arith.all;

entity tb_FIR is
end entity tb_FIR;

architecture tb_FIR_behavioural of tb_FIR is
  constant clk_period : time     := 10 ns;
  constant nr_of_taps : positive := 5;
  constant width      : positive := 5;

  component FIR_Toplevel
    port (rst_n      : in std_logic;
          clk        : in std_logic;
          sample_clk : in std_logic;
          sample     : in std_logic_vector(3 downto 0);
          dav  : out std_logic;
          outp : out std_logic_vector(3 downto 0)
          );
  end component;

  signal clk, sample_clk        : std_logic := '0';
  signal rst_n, dav_wire        : std_logic;
  signal sample_wire, outp_wire : std_logic_vector(3 downto 0);

begin

  rst_n <= '0',
           '1' after 2 ns;
  
  clk <= not clk after clk_period/2;

  smpl_clk : process
  begin  -- process smpl_clk

    sample_clk <= '0';

    for i in 1 to nr_of_taps loop
      wait until clk'event and clk = '0';
    end loop;  -- iwait until clk'event and clk = '1';

    sample_clk <= '1';

    wait until clk'event and clk = '0';
    
  end process smpl_clk;

  sample_wire <= (others => '0'),
                 conv_std_logic_vector (1, width-1) after (nr_of_taps*clk_period),
                 conv_std_logic_vector (0, width-1) after ((nr_of_taps+1)*clk_period),
                 conv_std_logic_vector (2, width-1) after ((2*nr_of_taps+1)*clk_period),
                 (others => '0') after ((2*nr_of_taps+2)*clk_period);

  u1 : FIR_Toplevel port map(rst_n,
                           clk,
                           sample_clk,
                           sample_wire,
                           dav_wire,
                           outp_wire);

end tb_FIR_behavioural;

Lab2/LAB2/REPORTS/top_fir_50samples.vcd
$date
	Tue Nov 24 19:21:29 2015
$end
$version
	ModelSim Version 6.5
$end
$timescale
	1ns
$end
$scope module tb_fir $end
$var wire 1 ! clk $end
$var wire 1 " sample_clk $end
$var wire 1 # rst_n $end
$var wire 1 $ dav_wire $end
$var wire 1 % sample_wire [3] $end
$var wire 1 & sample_wire [2] $end
$var wire 1 ' sample_wire [1] $end
$var wire 1 ( sample_wire [0] $end
$var wire 1 ) outp_wire [3] $end
$var wire 1 * outp_wire [2] $end
$var wire 1 + outp_wire [1] $end
$var wire 1 , outp_wire [0] $end
$scope module u1 $end
$var wire 1 # rst_n $end
$var wire 1 ! clk $end
$var wire 1 " sample_clk $end
$var wire 1 % sample [3] $end
$var wire 1 & sample [2] $end
$var wire 1 ' sample [1] $end
$var wire 1 ( sample [0] $end
$var wire 1 $ dav $end
$var wire 1 ) outp [3] $end
$var wire 1 * outp [2] $end
$var wire 1 + outp [1] $end
$var wire 1 , outp [0] $end
$var wire 1 - coeficient_out_wire [3] $end
$var wire 1 . coeficient_out_wire [2] $end
$var wire 1 / coeficient_out_wire [1] $end
$var wire 1 0 coeficient_out_wire [0] $end
$var wire 1 1 sample_out_wire [3] $end
$var wire 1 2 sample_out_wire [2] $end
$var wire 1 3 sample_out_wire [1] $end
$var wire 1 4 sample_out_wire [0] $end
$var wire 1 5 outp_wire [3] $end
$var wire 1 6 outp_wire [2] $end
$var wire 1 7 outp_wire [1] $end
$var wire 1 8 outp_wire [0] $end
$var wire 1 9 coef_addr_wire [2] $end
$var wire 1 : coef_addr_wire [1] $end
$var wire 1 ; coef_addr_wire [0] $end
$var wire 1 < dav_wire $end
$scope module u_delayline $end
$var wire 1 # rst_n $end
$var wire 1 ! clk $end
$var wire 1 " sample_clk $end
$var wire 1 % sample [3] $end
$var wire 1 & sample [2] $end
$var wire 1 ' sample [1] $end
$var wire 1 ( sample [0] $end
$var wire 1 1 sample_out [3] $end
$var wire 1 2 sample_out [2] $end
$var wire 1 3 sample_out [1] $end
$var wire 1 4 sample_out [0] $end
$var wire 1 = rws_wire $end
$var wire 1 > adrs_wire [2] $end
$var wire 1 ? adrs_wire [1] $end
$var wire 1 @ adrs_wire [0] $end
$var wire 1 A sample_write [3] $end
$var wire 1 B sample_write [2] $end
$var wire 1 C sample_write [1] $end
$var wire 1 D sample_write [0] $end
$var wire 1 E sample_out_wire [3] $end
$var wire 1 F sample_out_wire [2] $end
$var wire 1 G sample_out_wire [1] $end
$var wire 1 H sample_out_wire [0] $end
$scope module u30_cbram $end
$var wire 1 # rst_n $end
$var wire 1 = rws $end
$var wire 1 > addrs [2] $end
$var wire 1 ? addrs [1] $end
$var wire 1 @ addrs [0] $end
$var wire 1 A inp [3] $end
$var wire 1 B inp [2] $end
$var wire 1 C inp [1] $end
$var wire 1 D inp [0] $end
$var wire 1 E outp [3] $end
$var wire 1 F outp [2] $end
$var wire 1 G outp [1] $end
$var wire 1 H outp [0] $end
$upscope $end
$upscope $end
$scope module u_firp $end
$var wire 1 # rst_n $end
$var wire 1 ! clk $end
$var wire 1 " sample_clk $end
$var wire 1 1 sample_delay_in [3] $end
$var wire 1 2 sample_delay_in [2] $end
$var wire 1 3 sample_delay_in [1] $end
$var wire 1 4 sample_delay_in [0] $end
$var wire 1 - coeficient [3] $end
$var wire 1 . coeficient [2] $end
$var wire 1 / coeficient [1] $end
$var wire 1 0 coeficient [0] $end
$var wire 1 9 coef_addr [2] $end
$var wire 1 : coef_addr [1] $end
$var wire 1 ; coef_addr [0] $end
$var wire 1 < dav $end
$var wire 1 5 outp [3] $end
$var wire 1 6 outp [2] $end
$var wire 1 7 outp [1] $end
$var wire 1 8 outp [0] $end
$var wire 1 I accumulator [7] $end
$var wire 1 J accumulator [6] $end
$var wire 1 K accumulator [5] $end
$var wire 1 L accumulator [4] $end
$var wire 1 M accumulator [3] $end
$var wire 1 N accumulator [2] $end
$var wire 1 O accumulator [1] $end
$var wire 1 P accumulator [0] $end
$var wire 1 Q dav_wire $end
$var wire 1 R outp_wire [3] $end
$var wire 1 S outp_wire [2] $end
$var wire 1 T outp_wire [1] $end
$var wire 1 U outp_wire [0] $end
$var wire 1 V coef_addr_wire [2] $end
$var wire 1 W coef_addr_wire [1] $end
$var wire 1 X coef_addr_wire [0] $end
$upscope $end
$scope module u_rom $end
$var wire 1 9 address [2] $end
$var wire 1 : address [1] $end
$var wire 1 ; address [0] $end
$var wire 1 - coeficient_out [3] $end
$var wire 1 . coeficient_out [2] $end
$var wire 1 / coeficient_out [1] $end
$var wire 1 0 coeficient_out [0] $end
$upscope $end
$upscope $end
$upscope $end
$enddefinitions $end
#20
$dumpvars
0!
0"
1#
0$
0<
1=
0Q
0%
0&
0'
0(
0)
0*
0+
0,
0-
1.
0/
00
01
02
03
04
05
06
07
08
09
1:
1;
0>
1?
1@
0A
0B
0C
0D
0E
0F
0G
0H
0I
0J
0K
0L
0M
0N
0O
0P
0R
0S
0T
0U
0V
1W
1X
$end
#21
1!
0@
0?
1>
0X
0W
1V
0;
0:
19
0.
1-
#22
0!
1"
1(
1'
#23
1!
0=
1D
1C
0V
1Q
09
1<
10
0-
1$
#24
0!
0"
#25
1!
1=
0Q
1H
1G
0<
14
13
0$
#26
0!
#27
1!
0>
1P
1O
1X
0H
0G
1;
04
03
00
1/
#28
0!
#29
1!
1@
0X
1W
0;
1:
10
#30
0!
#31
1!
0@
1?
1X
1;
00
0/
1.
#32
0!
#33
1!
1@
0X
0W
1V
0;
0:
19
0.
1-
#34
0!
1"
1&
1%
#35
1!
0=
1B
1A
0V
0P
0O
1U
1T
1Q
09
18
17
1<
10
0-
1,
1+
1$
#36
0!
0"
#37
1!
1=
0Q
1H
1G
1F
1E
0<
14
13
12
11
0$
#38
0!
#39
1!
0@
0?
1>
1P
1O
1N
1M
1X
0F
0E
1;
02
01
00
1/
#40
0!
#41
1!
0>
0O
0M
1L
0X
1W
0H
0G
0;
1:
04
03
10
#42
0!
#43
1!
1@
1X
1;
00
0/
1.
#44
0!
#45
1!
0@
1?
0X
0W
1V
0;
0:
19
0.
1-
#46
0!
1"
0(
0&
0%
#47
1!
0=
0D
0B
0A
0V
0P
0N
0L
0T
1S
1Q
09
07
16
1<
10
0-
0+
1*
1$
#48
0!
0"
#49
1!
1=
0Q
1G
0<
13
0$
#50
0!
#51
1!
1@
1O
1X
1H
1F
1E
1;
14
12
11
00
1/
#52
0!
#53
1!
0@
0?
1>
0O
1K
0X
1W
0F
0E
0;
1:
02
01
10
#54
0!
#55
1!
0>
1P
1M
1X
0H
0G
1;
04
03
00
0/
1.
#56
0!
#57
1!
1@
0X
0W
1V
0;
0:
19
0.
1-
#58
0!
1"
0'
1&
1%
#59
1!
0=
0C
1B
1A
0V
0P
0M
0K
0S
1R
1Q
09
06
15
1<
10
0-
0*
1)
1$
#60
0!
0"
#61
1!
1=
0Q
1F
1E
0<
12
11
0$
#62
0!
#63
1!
0@
1?
1N
1M
1X
1G
0F
0E
1;
13
02
01
00
1/
#64
0!
#65
1!
1@
0N
0M
1L
0X
1W
1H
1F
1E
0;
1:
14
12
11
10
#66
0!
#67
1!
0@
0?
1>
1P
1N
1M
1K
1X
0F
0E
1;
02
01
00
0/
1.
#68
0!
#69
1!
0>
0N
0L
0K
1J
0X
0W
1V
0H
0G
0;
0:
19
04
03
0.
1-
#70
0!
1"
1(
0&
#71
1!
0=
1D
0B
0V
0P
0M
0J
1Q
09
1<
10
0-
1$
#72
0!
0"
#73
1!
1=
0Q
1H
1E
0<
14
11
0$
#74
0!
#75
1!
1@
1P
1M
1X
0H
1F
1;
04
12
00
1/
#76
0!
#77
1!
0@
1?
0M
1K
0X
1W
1G
0F
0E
0;
1:
13
02
01
10
#78
0!
#79
1!
1@
1O
1N
1X
1H
1F
1E
1;
14
12
11
00
0/
1.
#80
0!
#81
1!
0@
0?
1>
0N
1J
0X
0W
1V
0F
0E
0;
0:
19
02
01
0.
1-
#82
0!
1"
1'
0%
#83
1!
0=
1C
0A
0V
0P
0O
0K
0J
1T
0R
1Q
09
17
05
1<
10
0-
1+
0)
1$
#84
0!
0"
#85
1!
1=
0Q
0<
0$
#86
0!
#87
1!
0>
1P
1O
1X
0G
1E
1;
03
11
00
1/
#88
0!
#89
1!
1@
0O
1N
1L
0X
1W
0H
1F
0;
1:
04
12
10
#90
0!
#91
1!
0@
1?
0N
1M
1K
1X
1G
0F
0E
1;
13
02
01
00
0/
1.
#92
0!
#93
1!
1@
0M
0L
0K
1J
0X
0W
1V
1H
1F
1E
0;
0:
19
14
12
11
0.
1-
#94
0!
1"
1%
#95
1!
0=
1A
0V
0P
0J
0T
1Q
09
07
1<
10
0-
0+
1$
#96
0!
0"
#97
1!
1=
0Q
0F
0<
02
0$
#98
0!
#99
1!
0@
0?
1>
1P
1O
1M
1X
0E
1;
01
00
1/
#100
0!
#101
1!
0>
0O
0M
1L
0X
1W
0G
1E
0;
1:
03
11
10
#102
0!
#103
1!
1@
0P
1N
1M
0L
1K
1X
0H
1F
1;
04
12
00
0/
1.
#104
0!
#105
1!
0@
1?
1L
0K
1J
0X
0W
1V
1G
0F
0E
0;
0:
19
13
02
01
0.
1-
#106
0!
1"
1&
#107
1!
0=
1B
0V
0N
0M
0L
0J
0U
1S
1R
1Q
09
08
16
15
1<
10
0-
0,
1*
1)
1$
#108
0!
0"
#109
1!
1=
0Q
1H
1F
1E
0<
14
12
11
0$
#110
0!
#111
1!
1@
1P
1O
1N
1M
1X
0F
1;
02
00
1/
#112
0!
#113
1!
0@
0?
1>
0O
0M
1K
0X
1W
0E
0;
1:
01
10
#114
0!
#115
1!
0>
0P
1O
1M
1X
0G
1E
1;
03
11
00
0/
1.
#116
0!
#117
1!
1@
0N
0M
1L
0K
1J
0X
0W
1V
0H
1F
0;
0:
19
04
12
0.
1-
#118
0!
1"
0%
#119
1!
0=
0A
0V
0O
0L
0J
1T
0S
0R
1Q
09
17
06
05
1<
10
0-
1+
0*
0)
1$
#120
0!
0"
#121
1!
1=
0Q
1H
1G
0E
0<
14
13
01
0$
#122
0!
#123
1!
0@
1?
1P
1O
1N
1X
1E
1;
11
00
1/
#124
0!
#125
1!
1@
0O
1K
0X
1W
0F
0;
1:
02
10
#126
0!
#127
1!
0@
0?
1>
0P
1O
0K
1J
1X
0E
1;
01
00
0/
1.
#128
0!
#129
1!
0>
0N
1L
0X
0W
1V
0G
1E
0;
0:
19
03
11
0.
1-
#130
0!
1"
0(
#131
1!
0=
0D
0V
0O
0L
0J
1Q
09
1<
10
0-
1$
#132
0!
0"
#133
1!
1=
0Q
0H
1G
1F
0E
0<
04
13
12
01
0$
#134
0!
#135
1!
1@
1O
1N
1X
1H
1;
14
00
1/
#136
0!
#137
1!
0@
1?
0O
1L
0X
1W
1E
0;
1:
11
10
#138
0!
#139
1!
1@
1P
0N
0L
1J
1X
0F
1;
02
00
0/
1.
#140
0!
#141
1!
0@
0?
1>
1N
1M
1K
0X
0W
1V
0E
0;
0:
19
01
0.
1-
#142
0!
1"
1(
0'
0&
1%
#143
1!
0=
1D
0C
0B
1A
0V
0P
0N
0M
0K
0J
1U
0T
1S
1R
1Q
09
18
07
16
15
1<
10
0-
1,
0+
1*
1)
1$
#144
0!
0"
#145
1!
1=
0Q
0G
1E
0<
03
11
0$
#146
0!
#147
1!
0>
1P
1M
1X
0H
1G
1F
0E
1;
04
13
12
01
00
1/
#148
0!
#149
1!
1@
1N
0M
1L
0X
1W
1H
0;
1:
14
10
#150
0!
#151
1!
0@
1?
0P
1O
0N
1M
0L
1K
1X
1E
1;
11
00
0/
1.
#152
0!
#153
1!
1@
1N
0M
1J
0X
0W
1V
0F
0;
0:
19
02
0.
1-
#154
0!
1"
1&
#155
1!
0=
1B
0V
0O
0N
0K
0J
0U
1T
0R
1Q
09
08
17
05
1<
10
0-
0,
1+
0)
1$
#156
0!
0"
#157
1!
1=
0Q
0G
1F
0<
03
12
0$
#158
0!
#159
1!
0@
0?
1>
1P
1N
1M
1X
0F
1;
02
00
1/
#160
0!
#161
1!
0>
1O
1L
0X
1W
0H
1G
1F
0E
0;
1:
04
13
12
01
10
#162
0!
#163
1!
1@
0O
0N
0M
1K
1X
1H
1;
14
00
0/
1.
#164
0!
#165
1!
0@
1?
1N
1M
0L
0K
1J
0X
0W
1V
1E
0;
0:
19
11
0.
1-
#166
0!
1"
1'
#167
1!
0=
1C
0V
0P
0N
0M
0J
1U
0T
1R
1Q
09
18
07
15
1<
10
0-
1,
0+
1)
1$
#168
0!
0"
#169
1!
1=
0Q
0<
0$
#170
0!
#171
1!
1@
1P
1O
1N
1M
1X
0G
1;
03
00
1/
#172
0!
#173
1!
0@
0?
1>
0O
0N
1K
0X
1W
0F
0;
1:
02
10
#174
0!
#175
1!
0>
0P
1N
0M
0K
1J
1X
0H
1G
1F
0E
1;
04
13
12
01
00
0/
1.
#176
0!
#177
1!
1@
1M
1L
0X
0W
1V
1H
0;
0:
19
14
0.
1-
#178
0!
1"
0(
0'
0&
#179
1!
0=
0D
0C
0B
0V
0N
0M
0L
0J
0U
1Q
09
08
1<
10
0-
0,
1$
#180
0!
0"
#181
1!
1=
0Q
0H
0G
0F
1E
0<
04
03
02
11
0$
#182
0!
#183
1!
0@
1?
1M
1X
1H
1G
1F
1;
14
13
12
00
1/
#184
0!
#185
1!
1@
1O
1N
0M
1K
0X
1W
0G
0;
1:
03
10
#186
0!
#187
1!
0@
0?
1>
1P
0O
1M
0K
1J
1X
0F
1;
02
00
0/
1.
#188
0!
#189
1!
0>
0N
0M
1L
1K
0X
0W
1V
0H
1G
1F
0E
0;
0:
19
04
13
12
01
0.
1-
#190
0!
1"
1'
0%
#191
1!
0=
1C
0A
0V
0P
0L
0K
0J
1U
0S
0R
1Q
09
18
06
05
1<
10
0-
1,
0*
0)
1$
#192
0!
0"
#193
1!
1=
0Q
0F
0<
02
0$
#194
0!
#195
1!
1@
1O
1X
0G
1E
1;
03
11
00
1/
#196
0!
#197
1!
0@
1?
1L
0X
1W
1H
1G
1F
0;
1:
14
13
12
10
#198
0!
#199
1!
1@
1P
1N
1M
1K
1X
0G
1;
03
00
0/
1.
#200
0!
#201
1!
0@
0?
1>
0N
0M
1J
0X
0W
1V
0F
0;
0:
19
02
0.
1-
#202
0!
1"
1&
#203
1!
0=
1B
0V
0P
0O
0L
0K
0J
1T
1Q
09
17
1<
10
0-
1+
1$
#204
0!
0"
#205
1!
1=
0Q
0H
1G
1F
0E
0<
04
13
12
01
0$
#206
0!
#207
1!
0>
1O
1N
1X
0F
1;
02
00
1/
#208
0!
#209
1!
1@
0N
1M
0X
1W
0G
1E
0;
1:
03
11
10
#210
0!
#211
1!
0@
1?
0M
1K
1X
1H
1G
1F
1;
14
13
12
00
0/
1.
#212
0!
#213
1!
1@
1N
1M
1L
0K
1J
0X
0W
1V
0G
0;
0:
19
03
0.
1-
#214
0!
1"
0&
1%
#215
1!
0=
0B
1A
0V
0O
0N
0M
0L
0J
0U
1S
1R
1Q
09
08
16
15
1<
10
0-
0,
1*
1)
1$
#216
0!
0"
#217
1!
1=
0Q
0H
1G
0F
0<
04
13
02
0$
#218
0!
#219
1!
0@
0?
1>
1O
1M
1X
1F
0E
1;
12
01
00
1/
#220
0!
#221
1!
0>
1N
0M
1L
0X
1W
0F
0;
1:
02
10
#222
0!
#223
1!
1@
0O
1M
1X
0G
1E
1;
03
11
00
0/
1.
#224
0!
#225
1!
0@
1?
1K
0X
0W
1V
1H
1G
1F
0;
0:
19
14
13
12
0.
1-
#226
0!
1"
1(
0%
#227
1!
0=
1D
0A
0V
0N
0M
0L
0K
0T
1Q
09
07
1<
10
0-
0+
1$
#228
0!
0"
#229
1!
1=
0Q
0F
0E
0<
02
01
0$
#230
0!
#231
1!
1@
1P
1O
1X
0H
1E
1;
04
11
00
1/
#232
0!
#233
1!
0@
0?
1>
1N
1L
0X
1W
1F
0E
0;
1:
12
01
10
#234
0!
#235
1!
0>
0O
0N
1M
0L
1K
1X
0F
1;
02
00
0/
1.
#236
0!
#237
1!
1@
0M
1L
0X
0W
1V
0G
1E
0;
0:
19
03
11
0.
1-
#238
0!
1"
0(
1&
#239
1!
0=
0D
1B
0V
0P
0L
0K
1U
0S
0R
1Q
09
18
06
05
1<
10
0-
1,
0*
0)
1$
#240
0!
0"
#241
1!
1=
0Q
1G
1F
0E
0<
13
12
01
0$
#242
0!
#243
1!
0@
1?
1O
1N
1X
1H
0F
1;
14
02
00
1/
#244
0!
#245
1!
1@
0O
1M
0X
1W
0H
1E
0;
1:
04
11
10
#246
0!
#247
1!
0@
0?
1>
1O
0N
1K
1X
1F
0E
1;
12
01
00
0/
1.
#248
0!
#249
1!
0>
0M
0K
1J
0X
0W
1V
0F
0;
0:
19
02
0.
1-
#250
0!
1"
0'
0&
1%
#251
1!
0=
0C
0B
1A
0V
0O
0J
0U
1T
1Q
09
08
17
1<
10
0-
0,
1+
1$
#252
0!
0"
#253
1!
1=
0Q
0G
1E
0<
03
11
0$
#254
0!
#255
1!
1@
1M
1X
1G
1F
0E
1;
13
12
01
00
1/
#256
0!
#257
1!
0@
1?
1N
0M
1L
0X
1W
1H
0F
0;
1:
14
02
10
#258
0!
#259
1!
1@
1P
1M
1X
0H
1E
1;
04
11
00
0/
1.
#260
0!
#261
1!
0@
0?
1>
0M
0L
1J
0X
0W
1V
1F
0E
0;
0:
19
12
01
0.
1-
#262
0!
1"
1'
#263
1!
0=
1C
0V
0P
0N
0J
1U
0T
1S
1Q
09
18
07
16
1<
10
0-
1,
0+
1*
1$
#264
0!
0"
#265
1!
1=
0Q
0F
1E
0<
02
11
0$
#266
0!
#267
1!
0>
1O
1M
1X
0G
1;
03
00
1/
#268
0!
#269
1!
1@
1L
0X
1W
1G
1F
0E
0;
1:
13
12
01
10
#270
0!
#271
1!
0@
1?
0O
1N
0L
1K
1X
1H
0F
1;
14
02
00
0/
1.
#272
0!
#273
1!
1@
0N
1L
0X
0W
1V
0H
1E
0;
0:
19
04
11
0.
1-
#274
0!
1"
1(
0'
#275
1!
0=
1D
0C
0V
0M
0L
0K
0U
0S
1R
1Q
09
08
06
15
1<
10
0-
0,
0*
1)
1$
#276
0!
0"
#277
1!
1=
0Q
1H
0G
0<
14
03
0$
#278
0!
#279
1!
0@
0?
1>
1P
1M
1X
0H
1G
1;
04
13
00
1/
#280
0!
#281
1!
0>
1N
1L
0X
1W
0G
0;
1:
03
10
#282
0!
#283
1!
1@
0M
1K
1X
1G
1F
0E
1;
13
12
01
00
0/
1.
#284
0!
#285
1!
0@
1?
1M
0L
0K
1J
0X
0W
1V
1H
0F
0;
0:
19
14
02
0.
1-
#286
0!
1"
1'
#287
1!
0=
1C
0V
0P
0N
0M
0J
1U
1S
1Q
09
18
16
1<
10
0-
1,
1*
1$
#288
0!
0"
#289
1!
1=
0Q
1E
0<
11
0$
